{"status": 1, "can_edit": false, "is_automated": false, "last_updated": "2016-11-29T20:20:52.682843Z", "description": "Ubuntu is a Debian-based Linux operating system based on free software.", "tags": ["12.04.5", "12.04", "precise-20161123", "precise", "14.04.5", "14.04", "trusty-20161123", "trusty", "16.04", "xenial-20161121", "xenial", "latest", "16.10", "yakkety-20161121", "yakkety", "17.04", "zesty-20161129.1", "zesty", "devel"], "url": "https://hub.docker.com/_/ubuntu/", "pic": "https://hub.docker.com/public/images/official/ubuntu.png", "namespace": "library", "star_count": 5123, "user": "library", "pull_count": 142378740, "repository_type": null, "is_private": false, "name": "ubuntu"}